[
  { "name": "spec-discuss", "trigger": "/spec-discuss", "description": "Start discovery interview. Gather requirements, constraints, risks.", "category": "spec-mode", "args": "[session-name]" },
  { "name": "spec-plan", "trigger": "/spec-plan", "description": "Create SPEC + BLUEPRINT from REQUIREMENTS. Lock spec before execute.", "category": "spec-mode" },
  { "name": "spec-execute", "trigger": "/spec-execute", "description": "Begin wave-based implementation. Dispatches executor agents per wave.", "category": "spec-mode" },
  { "name": "spec-audit", "trigger": "/spec-audit", "description": "Dispatch verifier in fresh context against validation contract.", "category": "spec-mode" },
  { "name": "spec-accept", "trigger": "/spec-accept", "description": "Final acceptance gate. Requires user confirmation.", "category": "spec-mode" },
  { "name": "spec-status", "trigger": "/spec-status", "description": "Show current workflow phase, wave progress, spec lock state.", "category": "spec-mode" },
  { "name": "spec-amend", "trigger": "/spec-amend", "description": "Propose a change to a locked spec via the amendment flow.", "category": "spec-mode" },
  { "name": "spec-help", "trigger": "/spec-help", "description": "List all Spec Mode commands with descriptions.", "category": "spec-mode" },
  { "name": "spec-pause", "trigger": "/spec-pause", "description": "Save checkpoint and pause. Generates HANDOFF.md.", "category": "spec-mode" },
  { "name": "spec-resume", "trigger": "/spec-resume", "description": "Resume from last checkpoint.", "category": "spec-mode" },
  { "name": "spec-quick", "trigger": "/spec-quick", "description": "Fast-track a small task. Runs full pipeline in lazy autopilot.", "category": "spec-mode", "args": "<task description>" },
  { "name": "spec-research", "trigger": "/spec-research", "description": "Dispatch researcher agent on a specific topic.", "category": "spec-mode", "args": "<topic>" },
  { "name": "spec-debug", "trigger": "/spec-debug", "description": "Dispatch debugger with scientific debugging workflow.", "category": "spec-mode" },
  { "name": "spec-map-codebase", "trigger": "/spec-map-codebase", "description": "Dispatch explorer to map codebase and build knowledge base.", "category": "spec-mode" },
  { "name": "spec-pr-review", "trigger": "/spec-pr-review", "description": "Review a GitHub PR end-to-end with fix options.", "category": "spec-mode", "args": "<pr-url>" }
]
